kiauto/__init__.py
kiauto/file_util.py
kiauto/interposer.py
kiauto/log.py
kiauto/misc.py
kiauto/ui_automation.py
kiauto/interposer/libinterposer.so
kiauto-2.3.5.data/scripts/eeschema_do
kiauto-2.3.5.data/scripts/kicad2step_do
kiauto-2.3.5.data/scripts/pcbnew_do
src/eeschema_do
src/kicad2step_do
src/pcbnew_do
tests/conftest.py
tests/eeschema/test_bom_xml.py
tests/eeschema/test_erc.py
tests/eeschema/test_export.py
tests/eeschema/test_netlist.py
tests/eeschema/test_sch_misc.py
tests/kicad2step/test_step.py
tests/pcbnew/test_3d.py
tests/pcbnew/test_drc.py
tests/pcbnew/test_export_gencad.py
tests/pcbnew/test_export_vrml.py
tests/pcbnew/test_pcb_misc.py
tests/pcbnew/test_print_layers.py
tests/utils/context.py
kiauto-2.3.5.dist-info/LICENSE
kiauto-2.3.5.dist-info/METADATA
kiauto-2.3.5.dist-info/WHEEL
kiauto-2.3.5.dist-info/top_level.txt
kiauto-2.3.5.dist-info/RECORD
