Metadata-Version: 2.1
Name: kiauto
Version: 2.3.5
Summary: KiCad Automation Scripts
Home-page: https://github.com/INTI-CMNB/KiAuto/
Author: Salvador E. Tropea
Author-email: stropea@inti.gob.ar
License: Apache License 2.0
Platform: POSIX
Classifier: Development Status :: 4 - Beta
Classifier: Environment :: Console
Classifier: Intended Audience :: Developers
Classifier: License :: OSI Approved :: Apache Software License
Classifier: Natural Language :: English
Classifier: Operating System :: POSIX :: Linux
Classifier: Programming Language :: Python :: 3
Classifier: Topic :: Scientific/Engineering :: Electronic Design Automation (EDA)
Requires-Python: >=3.4
Requires-Dist: psutil
Requires-Dist: xvfbwrapper
